neopika/__init__.py
neopika/analytics.py
neopika/dialects.py
neopika/enums.py
neopika/functions.py
neopika/pseudocolumns.py
neopika/py.typed
neopika/queries.py
neopika/terms.py
neopika/utils.py
neopika/clickhouse/__init__.py
neopika/clickhouse/array.py
neopika/clickhouse/condition.py
neopika/clickhouse/dates_and_times.py
neopika/clickhouse/nullable_arg.py
neopika/clickhouse/search_string.py
neopika/clickhouse/type_conversion.py
neopika/tests/__init__.py
neopika/tests/test_aggregate.py
neopika/tests/test_analytic_queries.py
neopika/tests/test_create.py
neopika/tests/test_criterions.py
neopika/tests/test_custom_functions.py
neopika/tests/test_data_types.py
neopika/tests/test_date_math.py
neopika/tests/test_deletes.py
neopika/tests/test_drop.py
neopika/tests/test_formats.py
neopika/tests/test_functions.py
neopika/tests/test_groupby_modifiers.py
neopika/tests/test_immutability.py
neopika/tests/test_inserts.py
neopika/tests/test_internals.py
neopika/tests/test_joins.py
neopika/tests/test_negation.py
neopika/tests/test_parameter.py
neopika/tests/test_pseudocolumns.py
neopika/tests/test_query.py
neopika/tests/test_selects.py
neopika/tests/test_tables.py
neopika/tests/test_terms.py
neopika/tests/test_tuples.py
neopika/tests/test_updates.py
neopika/tests/test_utils.py
neopika/tests/clickhouse/__init__.py
neopika/tests/clickhouse/test_array.py
neopika/tests/clickhouse/test_condition.py
neopika/tests/clickhouse/test_dates_and_times.py
neopika/tests/clickhouse/test_nullable_arg.py
neopika/tests/clickhouse/test_search_string.py
neopika/tests/clickhouse/test_type_conversion.py
neopika/tests/dialects/__init__.py
neopika/tests/dialects/test_clickhouse.py
neopika/tests/dialects/test_mssql.py
neopika/tests/dialects/test_mysql.py
neopika/tests/dialects/test_oracle.py
neopika/tests/dialects/test_postgresql.py
neopika/tests/dialects/test_snowflake.py
neopika/tests/dialects/test_sqllite.py
neopika/tests/dialects/test_vertica.py
neopika-0.49.0.dist-info/METADATA
neopika-0.49.0.dist-info/WHEEL
neopika-0.49.0.dist-info/licenses/LICENSE.txt
neopika-0.49.0.dist-info/RECORD
