Metadata-Version: 2.4
Name: NeoPika
Version: 0.49.0
Summary: A SQL query builder API for Python
Project-URL: Homepage, https://github.com/kayak/neopika
License: Apache License Version 2.0
License-File: LICENSE.txt
Keywords: aggregated,analysis,bi,business analytics,data science,mysql,neopika,object mapper,oracle,orm,pandas,postgres,psql,python,query builder,querybuilder,rdbms,relational database,sql,vertica
Classifier: Development Status :: 5 - Production/Stable
Classifier: Intended Audience :: Developers
Classifier: License :: OSI Approved :: Apache Software License
Classifier: Operating System :: MacOS :: MacOS X
Classifier: Operating System :: Microsoft :: Windows
Classifier: Operating System :: POSIX
Classifier: Programming Language :: PL/SQL
Classifier: Programming Language :: Python :: 3
Classifier: Topic :: Scientific/Engineering :: Information Analysis
Classifier: Topic :: Scientific/Engineering :: Mathematics
Classifier: Topic :: Software Development :: Libraries :: Python Modules
Requires-Python: >=3.9
